setup.py
graphics.py.egg-info/PKG-INFO
graphics.py.egg-info/SOURCES.txt
graphics.py.egg-info/dependency_links.txt
graphics.py.egg-info/not-zip-safe
graphics.py.egg-info/requires.txt
graphics.py.egg-info/top_level.txt
graphics_py/__init__.py