Metadata-Version: 1.0
Name: graphics.py
Version: 0.1
Summary: John Zelles graphics.py package, for use with the textbook "Python Programming: An Introduction to Computer Science"
Home-page: UNKNOWN
Author: John M. Zelle (package maintainer: Patrick Narkinsky)
Author-email: patrick@narkinsky.com
License: GPL
Platform: UNKNOWN
